{
  "project_info": {
    "project_number": "1070842956676",
    "project_id": "wilsondissertation-7d8e2",
    "storage_bucket": "wilsondissertation-7d8e2.appspot.com"
  },
  "client": [
    {
      "client_info": {
        "mobilesdk_app_id": "1:1070842956676:android:f2d5577ed6a3f51c9debd1",
        "android_client_info": {
          "package_name": "com.example.accident_app"
        }
      },
      "oauth_client": [],
      "api_key": [
        {
          "current_key": "AIzaSyDrAmOyMR4jnahAuZReaHTdV81ue89vZ9g"
        }
      ],
      "services": {
        "appinvite_service": {
          "other_platform_oauth_client": []
        }
      }
    }
  ],
  "configuration_version": "1"
}